docs/conf.py
examples/derivatives_strategy.py
examples/derivatives_strategy_02.py
examples/derivatives_strategy_03.py
examples/get_available_stocks.py
examples/get_internale_ohlc_handler.py
examples/get_public_ohlc_handler.py
examples/get_ta_function_docs.py
examples/gpt_ta.py
examples/smc_ta.py
examples/strategy.py
examples/strategy_bollinger_bands.py
examples/strategy_momentum_breakout.py
examples/strategy_multi_indicator.py
examples/strategy_sma_crossover.py
examples/ta_example.py
examples/test_ta.py
xno/__init__.py
xno/config.py
xno/doc_api.py
xno/exceptions.py
xno/version.py
xno/algo/__init__.py
xno/algo/_base.py
xno/algo/dv.py
xno/algo/features.py
xno/algo/st.py
xno/analytics/__init__.py
xno/analytics/performances.py
xno/analytics/vs.py
xno/cli/__init__.py
xno/data/__init__.py
xno/data/datasources/__init__.py
xno/data/datasources/internal/__init__.py
xno/data/datasources/internal/ohlc/__init__.py
xno/data/datasources/public/__init__.py
xno/data/datasources/public/ohlc/__init__.py
xno/data/handlers/__init__.py
xno/data/handlers/ohlc/__init__.py
xno/platform/__init__.py
xno/platform/ta/__init__.py
xno/platform/ta/docs/__init__.py
xno/platform/ta/expressions/__init__.py
xno/platform/ta/stocks/__init__.py
xno/protoc/__init__.py
xno/protoc/websocket_message_pb2.py
xno/signals/__init__.py
xno/timeseries/__init__.py
xno/timeseries/_internal.py
xno/timeseries/math/__init__.py
xno/timeseries/pattern/__init__.py
xno/timeseries/pattern/candles/__init__.py
xno/timeseries/pattern/charts/__init__.py
xno/timeseries/price/__init__.py
xno/timeseries/rank/__init__.py
xno/timeseries/smc/__init__.py
xno/timeseries/smc/bos/__init__.py
xno/timeseries/smc/fvg/__init__.py
xno/timeseries/smc/ob/__init__.py
xno/timeseries/smc/swings/__init__.py
xno/timeseries/statistical/__init__.py
xno/timeseries/technicals/__init__.py
xno/timeseries/technicals/htf/__init__.py
xno/timeseries/technicals/momentum/__init__.py
xno/timeseries/technicals/overlap/__init__.py
xno-0.1.0.dist-info/METADATA
xno-0.1.0.dist-info/WHEEL
xno-0.1.0.dist-info/top_level.txt
xno-0.1.0.dist-info/RECORD
