Metadata-Version: 2.4
Name: xno
Version: 0.1.0
Summary: XNO Package for Quantitative Finance
Author-email: Kim <kim.nguyen@xno.vn>
License: MIT License
